{
	"format_version": "1.12.0",
	"minecraft:geometry": [
		{
			"description": {
				"identifier": "geometry.pirarucu",
				"texture_width": 128,
				"texture_height": 128,
				"visible_bounds_width": 5,
				"visible_bounds_height": 2.5,
				"visible_bounds_offset": [0, 0.75, 0]
			},
			"bones": [
				{
					"name": "pirarucu",
					"pivot": [0, 0, 0]
				},
				{
					"name": "body",
					"parent": "pirarucu",
					"pivot": [0.5, 0, -11],
					"cubes": [
						{"origin": [-4.5, 0, -12], "size": [9, 12, 33], "uv": [0, 0]}
					]
				},
				{
					"name": "neck",
					"parent": "body",
					"pivot": [0.5, 4, -7]
				},
				{
					"name": "fin_left",
					"parent": "body",
					"pivot": [-5.5, 1, -8],
					"cubes": [
						{"origin": [-11.5, 1, -11], "size": [7, 0, 7], "uv": [0, 0]}
					]
				},
				{
					"name": "fin_right",
					"parent": "body",
					"pivot": [5.5, 1, -8],
					"cubes": [
						{"origin": [4.5, 1, -11], "size": [7, 0, 7], "uv": [0, 0], "mirror": true}
					]
				},
				{
					"name": "fin_top",
					"parent": "body",
					"pivot": [0, 12, 10],
					"cubes": [
						{"origin": [0, 11, 10], "size": [0, 4, 14], "uv": [0, 0]}
					]
				},
				{
					"name": "fin_bottom",
					"parent": "body",
					"pivot": [0, 0, 14],
					"cubes": [
						{"origin": [0, -3, 14], "size": [0, 4, 9], "uv": [0, 9]}
					]
				},
				{
					"name": "tail",
					"parent": "body",
					"pivot": [0, 6, 21],
					"cubes": [
						{"origin": [0, 3, 21], "size": [0, 7, 5], "uv": [0, 17]}
					]
				},
				{
					"name": "head",
					"parent": "pirarucu",
					"pivot": [0.5, 2, -14],
					"cubes": [
						{"origin": [-4.5, 0, -20], "size": [9, 6, 8], "uv": [0, 45]}
					]
				}
			]
		}
	]
}